flexNetSim-0.26.dist-info/DESCRIPTION.rst
flexNetSim-0.26.dist-info/METADATA
flexNetSim-0.26.dist-info/RECORD
flexNetSim-0.26.dist-info/WHEEL
flexNetSim-0.26.dist-info/metadata.json
flexNetSim-0.26.dist-info/top_level.txt
flexnetsim/__init__.py
flexnetsim/bitrate.py
flexnetsim/connection.py
flexnetsim/controller.py
flexnetsim/event.py
flexnetsim/link.py
flexnetsim/network.py
flexnetsim/node.py
flexnetsim/simulator.py
flexnetsim/random/pyexpvariable.cpp
flexnetsim/random/pyexpvariable.cpython-37m-x86_64-linux-gnu.so
flexnetsim/random/pyunivariable.cpp
flexnetsim/random/pyunivariable.cpython-37m-x86_64-linux-gnu.so
